numpy_ext/__init__.py
numpy_ext/numpy_ext.py
numpy_extension-0.0.1.2.1.dist-info/LICENSE
numpy_extension-0.0.1.2.1.dist-info/METADATA
numpy_extension-0.0.1.2.1.dist-info/WHEEL
numpy_extension-0.0.1.2.1.dist-info/top_level.txt
numpy_extension-0.0.1.2.1.dist-info/RECORD
