Metadata-Version: 2.1
Name: numpy_extension
Version: 0.0.1.2.1
Summary: This Python package extends the functionality of numpy by introducing additional methods for data manipulation, and a specialized format for reading and writing numpy arrays.
Author-email: Caewinix <Caewinix@yeah.net>
Project-URL: Homepage, https://github.com/Caewinix/numpy_extension
Project-URL: Bug Tracker, https://github.com/Caewinix/numpy_extension/issues
Classifier: Programming Language :: Python :: 3
Classifier: License :: OSI Approved :: MIT License
Classifier: Operating System :: OS Independent
Requires-Python: >=3.7
License-File: LICENSE
Requires-Dist: numpy
Requires-Dist: array-like-generic
Requires-Dist: sortedcontainers
